fixtures/__init__.py
fixtures/_version.py
fixtures/callmany.py
fixtures/fixture.py
fixtures/testcase.py
fixtures/_fixtures/__init__.py
fixtures/_fixtures/environ.py
fixtures/_fixtures/logger.py
fixtures/_fixtures/mockpatch.py
fixtures/_fixtures/monkeypatch.py
fixtures/_fixtures/packagepath.py
fixtures/_fixtures/popen.py
fixtures/_fixtures/pythonpackage.py
fixtures/_fixtures/pythonpath.py
fixtures/_fixtures/streams.py
fixtures/_fixtures/tempdir.py
fixtures/_fixtures/temphomedir.py
fixtures/_fixtures/timeout.py
fixtures/_fixtures/warnings.py
fixtures/tests/__init__.py
fixtures/tests/helpers.py
fixtures/tests/test_callmany.py
fixtures/tests/test_fixture.py
fixtures/tests/test_testcase.py
fixtures/tests/_fixtures/__init__.py
fixtures/tests/_fixtures/test_environ.py
fixtures/tests/_fixtures/test_logger.py
fixtures/tests/_fixtures/test_mockpatch.py
fixtures/tests/_fixtures/test_monkeypatch.py
fixtures/tests/_fixtures/test_packagepath.py
fixtures/tests/_fixtures/test_popen.py
fixtures/tests/_fixtures/test_pythonpackage.py
fixtures/tests/_fixtures/test_pythonpath.py
fixtures/tests/_fixtures/test_streams.py
fixtures/tests/_fixtures/test_tempdir.py
fixtures/tests/_fixtures/test_temphomedir.py
fixtures/tests/_fixtures/test_timeout.py
fixtures/tests/_fixtures/test_warnings.py
fixtures-4.2.3.post2.dist-info/METADATA
fixtures-4.2.3.post2.dist-info/WHEEL
fixtures-4.2.3.post2.dist-info/licenses/AUTHORS
fixtures-4.2.3.post2.dist-info/licenses/COPYING
fixtures-4.2.3.post2.dist-info/RECORD
