Metadata-Version: 2.4
Name: fixtures
Version: 4.2.3.post2
Summary: Fixtures, reusable state for writing clean tests and more.
Project-URL: Homepage, https://github.com/testing-cabal/fixtures
Project-URL: Bug Tracker, https://github.com/testing-cabal/fixtures/issues
Project-URL: Source Code, https://github.com/testing-cabal/fixtures
Author-email: Robert Collins <robertc@robertcollins.net>
License: Apache-2.0 or BSD
License-File: AUTHORS
License-File: COPYING
Classifier: Development Status :: 6 - Mature
Classifier: Intended Audience :: Developers
Classifier: License :: OSI Approved :: Apache Software License
Classifier: License :: OSI Approved :: BSD License
Classifier: Operating System :: OS Independent
Classifier: Programming Language :: Python
Classifier: Programming Language :: Python :: 3
Classifier: Programming Language :: Python :: 3.8
Classifier: Programming Language :: Python :: 3.9
Classifier: Programming Language :: Python :: 3.10
Classifier: Programming Language :: Python :: 3.11
Classifier: Programming Language :: Python :: 3.12
Classifier: Programming Language :: Python :: 3.13
Classifier: Programming Language :: Python :: Implementation :: CPython
Classifier: Programming Language :: Python :: Implementation :: PyPy
Classifier: Topic :: Software Development :: Quality Assurance
Classifier: Topic :: Software Development :: Testing
Requires-Python: >=3.8
Provides-Extra: docs
Requires-Dist: docutils; extra == 'docs'
Provides-Extra: streams
Requires-Dist: testools; extra == 'streams'
Provides-Extra: test
Requires-Dist: testtools; extra == 'test'
